raincoat/__init__.py
raincoat/__main__.py
raincoat/cli.py
raincoat/color.py
raincoat/constants.py
raincoat/exceptions.py
raincoat/github_utils.py
raincoat/glue.py
raincoat/grep.py
raincoat/match/__init__.py
raincoat/match/django.py
raincoat/match/pygithub.py
raincoat/match/pypi.py
raincoat/match/python.py
raincoat/metadata.py
raincoat/parse.py
raincoat/source.py
raincoat/utils.py
raincoat-1.2.4.dist-info/entry_points.txt
raincoat-1.2.4.dist-info/LICENSE.rst
raincoat-1.2.4.dist-info/WHEEL
raincoat-1.2.4.dist-info/METADATA
raincoat-1.2.4.dist-info/RECORD
