Metadata-Version: 2.1
Name: raincoat
Version: 1.2.4
Summary: Raincoat has you covered when you cannot stay DRY. Linter for copy-pasted code.
Home-page: https://raincoat.readthedocs.io/
License: MIT
Keywords: linter,copy-paste
Author: Joachim Jablon
Author-email: ewjoachim@gmail.com
Requires-Python: >=3.7,<4.0
Classifier: Development Status :: 5 - Production/Stable
Classifier: Intended Audience :: Developers
Classifier: License :: OSI Approved :: MIT License
Classifier: Programming Language :: Python :: 3
Classifier: Programming Language :: Python :: 3.7
Classifier: Programming Language :: Python :: 3.8
Classifier: Programming Language :: Python :: 3.9
Classifier: Programming Language :: Python :: 3.10
Classifier: Programming Language :: Python :: 3.11
Classifier: Programming Language :: Python :: 3
Classifier: Programming Language :: Python :: 3.10
Classifier: Programming Language :: Python :: 3.7
Classifier: Programming Language :: Python :: 3.8
Classifier: Programming Language :: Python :: 3.9
Requires-Dist: asttokens
Requires-Dist: click
Requires-Dist: colorama
Requires-Dist: importlib-metadata; python_version < "3.10"
Requires-Dist: requests
Requires-Dist: typing-extensions
Project-URL: Documentation, https://raincoat.readthedocs.io/
Project-URL: Repository, https://github.com/ewjoachim/raincoat
